domain_infomoto/__init__.py
domain_infomoto/camel_model/CamelModel.py
domain_infomoto/camel_model/__init__.py
domain_infomoto/models/TestModel.py
domain_infomoto/models/__init__.py
domain_infomoto-0.1.1.dist-info/WHEEL
domain_infomoto-0.1.1.dist-info/METADATA
domain_infomoto-0.1.1.dist-info/RECORD
