Metadata-Version: 2.1
Name: domain-infomoto
Version: 0.1.1
Summary: 
Author: todotom
Author-email: tomasdarioam@protonmail.com
Requires-Python: >=3.10,<4.0
Classifier: Programming Language :: Python :: 3
Classifier: Programming Language :: Python :: 3.10
Requires-Dist: pydantic (>=1.9.0,<2.0.0)
